novelai_gen-0.1.1.dist-info/METADATA
novelai_gen-0.1.1.dist-info/WHEEL
novelai_gen/__init__.py
novelai_gen/error.py
novelai_gen/hash.py
novelai_gen/schema.py
novelai_gen-0.1.1.dist-info/RECORD
