Metadata-Version: 2.1
Name: novelai_gen
Version: 0.1.1
Summary: Gen Image From Novelai
Author-Email: sudoskys <coldlando@hotmail.com>
License: MIT
Requires-Python: >=3.8
Requires-Dist: elara>=0.5.5
Requires-Dist: redis>=5.0.1
Requires-Dist: loguru>=0.7.2
Requires-Dist: pydantic-settings>=2.1.0
Requires-Dist: pydantic>=2.5.3
Requires-Dist: sentry-sdk>=1.39.2
Requires-Dist: httpx>=0.26.0
Requires-Dist: shortuuid>=1.0.11
Requires-Dist: Pillow>=10.2.0
Requires-Dist: curl-cffi>=0.5.10
Requires-Dist: dynaconf>=3.2.4
Requires-Dist: fastapi>=0.109.0
Requires-Dist: uvicorn[standard]>=0.26.0
Requires-Dist: opencv-python>=4.8.1.78
Requires-Dist: pytest>=7.4.4; extra == "testing"
Provides-Extra: testing
